clever_cache/__init__.py
clever_cache/apps.py
clever_cache/backend.py
clever_cache/lua.py
clever_cache/monkeypatch.py
clever_cache/utils.py
clever_cache/migrations/__init__.py
django_clever_cache-0.0.1.dist-info/DESCRIPTION.rst
django_clever_cache-0.0.1.dist-info/METADATA
django_clever_cache-0.0.1.dist-info/RECORD
django_clever_cache-0.0.1.dist-info/WHEEL
django_clever_cache-0.0.1.dist-info/metadata.json
django_clever_cache-0.0.1.dist-info/top_level.txt
tests/__init__.py
tests/settings.py
tests/testapp/__init__.py
tests/testapp/apps.py
tests/testapp/models.py
tests/testapp/tests.py
tests/testapp/migrations/0001_initial.py
tests/testapp/migrations/__init__.py
