Metadata-Version: 2.0
Name: django-clever-cache
Version: 0.0.1
Summary: Django cache backend with automatic granular invalidation
Home-page: https://github.com/RafGb/django-clever-cache
Author: Rafis Gubajdullin
Author-email: raf.gbd@gmail.com
License: MIT
Platform: UNKNOWN
Requires-Dist: django (>=1.8)
Requires-Dist: django-redis
